safuaaaa/__init__.py
safuaaaa/notebook_fetcher.py
noteeee-0.1.dist-info/METADATA
noteeee-0.1.dist-info/WHEEL
noteeee-0.1.dist-info/top_level.txt
noteeee-0.1.dist-info/RECORD
